core/__init__.py
core/telemetry/__init__.py
core/telemetry/otel.py
core/telemetry/posthog.py
core/telemetry/sentry.py
cua_core-0.1.16.dist-info/METADATA
cua_core-0.1.16.dist-info/WHEEL
cua_core-0.1.16.dist-info/entry_points.txt
cua_core-0.1.16.dist-info/RECORD
